common_ci_utils/__init__.py
common_ci_utils/command_runner.py
common_ci_utils/connection.py
common_ci_utils/exceptions.py
common_ci_utils/file_system_utils.py
common_ci_utils/host_info.py
common_ci_utils/models.py
common_ci_utils/package_fetcher.py
common_ci_utils/postgres_utils.py
common_ci_utils/random_utils.py
common_ci_utils/rpm_manager.py
common_ci_utils/service_manager.py
common_ci_utils/templating.py
common_ci_utils/url_utils.py
common_ci_utils/config/default.yaml
common_ci_utils/config/noobaa-sa/default.yaml
common_ci_utils-0.0.4.dist-info/LICENSE
common_ci_utils-0.0.4.dist-info/METADATA
common_ci_utils-0.0.4.dist-info/WHEEL
common_ci_utils-0.0.4.dist-info/top_level.txt
common_ci_utils-0.0.4.dist-info/RECORD
