Metadata-Version: 2.1
Name: common_ci_utils
Version: 0.0.4
Summary: Place for common utils, functionality and libraries used in the testing and CI.
Home-page: 
Author: IBM Storage QE
Author-email: IBM Storage QE <ocs-qe-ecosystem@redhat.com>
License: MIT License
Project-URL: Homepage, https://github.com/red-hat-storage/common-ci-utils
Project-URL: Bug Tracker, https://github.com/red-hat-storage/common-ci-utils/issues
Classifier: Programming Language :: Python :: 3
Classifier: Operating System :: OS Independent
Requires-Python: >=3.10
License-File: LICENSE
Requires-Dist: jinja2
Requires-Dist: paramiko
Requires-Dist: pyyaml
Requires-Dist: requests
